failSafePackage/__init__.py
failSafePackage/fail_safe_validation.py
failSafePackage-0.0.4.dist-info/Licence.txt
failSafePackage-0.0.4.dist-info/METADATA
failSafePackage-0.0.4.dist-info/WHEEL
failSafePackage-0.0.4.dist-info/top_level.txt
failSafePackage-0.0.4.dist-info/RECORD
