Metadata-Version: 2.1
Name: failSafePackage
Version: 0.0.4
Summary: This class is written to handeled fail-safe conditions for all PMS.
Author: Rahul Khose
License-File: Licence.txt
Requires-Dist: numpy (==1.21.5)
